uruwat/__init__.py
uruwat/async_client.py
uruwat/client.py
uruwat/exceptions.py
uruwat/models.py
uruwat-0.2.0.dist-info/METADATA
uruwat-0.2.0.dist-info/WHEEL
uruwat-0.2.0.dist-info/RECORD
